glassdome_waypoint/__init__.py
glassdome_waypoint/get_provider_info.py
glassdome_waypoint/hooks/__init__.py
glassdome_waypoint/hooks/waypoint.py
airflow_providers_glassdome_waypoint-0.1.1.dist-info/METADATA
airflow_providers_glassdome_waypoint-0.1.1.dist-info/WHEEL
airflow_providers_glassdome_waypoint-0.1.1.dist-info/entry_points.txt
airflow_providers_glassdome_waypoint-0.1.1.dist-info/top_level.txt
airflow_providers_glassdome_waypoint-0.1.1.dist-info/RECORD
