Metadata-Version: 2.4
Name: airflow-providers-glassdome-waypoint
Version: 0.1.1
Summary: Airflow provider for Glassdome Waypoint API.
Author-email: Glassdome <developer@glassdomeinc.com>
License: Proprietary
Requires-Python: >=3.10
Requires-Dist: apache-airflow>=2.11.0
Requires-Dist: apache-airflow-providers-common-compat>=1.8.0
Requires-Dist: glassdome-waypoint-sdk>=0.1.1
Provides-Extra: dev
Requires-Dist: apache-airflow-providers-fab[common.compat]>=2.0.0; extra == "dev"
